django_json_error_response/__init__.py
django_json_error_response/http.py
django_json_error_response-0.1.dist-info/LICENSE.txt
django_json_error_response-0.1.dist-info/METADATA
django_json_error_response-0.1.dist-info/WHEEL
django_json_error_response-0.1.dist-info/top_level.txt
django_json_error_response-0.1.dist-info/RECORD
