Metadata-Version: 2.1
Name: django-json-error-response
Version: 0.1
Summary: Json Response for http error codes
Home-page: https://github.com/subodh358/django_status_response
Author: Subodh Popalwar
Author-email: subodhpopalwar.345@gmail.com
License: MIT
Download-URL: https://github.com/subodh358/django_status_response/archive/v_01.tar.gz
Keywords: Django,HttpResponse,Response
Platform: UNKNOWN
Classifier: Development Status :: 3 - Alpha
Classifier: Intended Audience :: Developers
Classifier: Topic :: Software Development :: Build Tools
Classifier: License :: OSI Approved :: MIT License
Classifier: Programming Language :: Python :: 3
Classifier: Programming Language :: Python :: 3.4
Classifier: Programming Language :: Python :: 3.5
Classifier: Programming Language :: Python :: 3.6
Requires-Dist: django
